[
  {
    "Country":"Argentina",
    "Universities":102
  },
  {
    "Country":"Austria",
    "Universities":17
  },
  {
    "Country":"Belgium",
    "Universities":10
  },
  {
    "Country":"Bolivia",
    "Universities":50
  },
  {
    "Country":"Brazil",
    "Universities":153
  },
  {
    "Country":"Chile",
    "Universities":57
  },
  {
    "Country":"China",
    "Universities":2146
  },
  {
    "Country":"Colombia",
    "Universities":110
  },
  {
    "Country":"Costa Rica",
    "Universities":48
  },
  {
    "Country":"Czech Republic",
    "Universities":13
  },
  {
    "Country":"Denmark",
    "Universities":7
  },
  {
    "Country":"Dominican Republic",
    "Universities":26
  },
  {
    "Country":"Ecuador",
    "Universities":52
  },
  {
    "Country":"El Salvador",
    "Universities":23
  },
  {
    "Country":"Estonia",
    "Universities":9
  },
  {
    "Country":"France",
    "Universities":241
  },
  {
    "Country":"Germany",
    "Universities":70
  },
  {
    "Country":"Greece",
    "Universities":47
  },
  {
    "Country":"Greenland",
    "Universities":1
  },
  {
    "Country":"Guatemala",
    "Universities":11
  },
  {
    "Country":"Honduras",
    "Universities":12
  },
  {
    "Country":"Hong Kong",
    "Universities":7
  },
  {
    "Country":"Hungary",
    "Universities":19
  },
  {
    "Country":"Ireland",
    "Universities":48
  },
  {
    "Country":"Israel",
    "Universities":34
  },
  {
    "Country":"Italy",
    "Universities":51
  },
  {
    "Country":"Jamaica",
    "Universities":6
  },
  {
    "Country":"Luxembourg",
    "Universities":2
  },
  {
    "Country":"Mexico",
    "Universities":334
  },
  {
    "Country":"Nicaragua",
    "Universities":34
  },
  {
    "Country":"Norway",
    "Universities":13
  },
  {
    "Country":"Panama",
    "Universities":20
  },
  {
    "Country":"Paraguay",
    "Universities":9
  },
  {
    "Country":"Peru",
    "Universities":58
  },
  {
    "Country":"Poland",
    "Universities":49
  },
  {
    "Country":"Portugal",
    "Universities":66
  },
  {
    "Country":"Puerto Rico",
    "Universities":15
  },
  {
    "Country":"Russia",
    "Universities":386
  },
  {
    "Country":"Serbia",
    "Universities":10
  },
  {
    "Country":"Slovakia",
    "Universities":33
  },
  {
    "Country":"Slovenia",
    "Universities":4
  },
  {
    "Country":"South Africa",
    "Universities":1
  },
  {
    "Country":"Spain",
    "Universities":50
  },
  {
    "Country":"Sweden",
    "Universities":29
  },
  {
    "Country":"Switzerland",
    "Universities":30
  },
  {
    "Country":"The Netherlands",
    "Universities":61
  },
  {
    "Country":"The United Kingdom",
    "Universities":286
  },
  {
    "Country":"Turkey",
    "Universities":3
  },
  {
    "Country":"Ukraine",
    "Universities":133
  },
  {
    "Country":"United States",
    "Universities":4617
  },
  {
    "Country":"Uruguay",
    "Universities":6
  },
  {
    "Country":"Venezuela",
    "Universities":42
  }
]